consistentsamplerpkg/__init__.py
consistentsamplerpkg-1.0.2.dist-info/METADATA
consistentsamplerpkg-1.0.2.dist-info/RECORD
consistentsamplerpkg-1.0.2.dist-info/WHEEL
consistentsamplerpkg-1.0.2.dist-info/top_level.txt
